[{"name": "If-Exist", "img": {"x0Cord": "866", "x1Cord": "927", "y0Cord": "1029", "y1Cord": "1079", "img": "Screen0.png"}, "id": "0", "frame": "", "fatherIndex": "0", "fatherName": "If-Exist", "extra": {"image": "Screen0.png", "functions": [{"name": "If-Exist", "img": {"x0Cord": "804", "x1Cord": "861", "y0Cord": "1031", "y1Cord": "1079", "img": "Screen2.png"}, "id": "2", "frame": "", "fatherIndex": "0", "fatherName": "If-Exist", "extra": {"image": "Screen2.png", "functions": [{"name": "If-Exist", "img": {"x0Cord": "742", "x1Cord": "796", "y0Cord": "1032", "y1Cord": "1079", "img": "Screen4.png"}, "id": "4", "frame": "", "fatherIndex": "2", "fatherName": "If-Exist", "extra": {"image": "Screen4.png", "functions": [{"name": "Left-Click", "img": {"x0Cord": "866", "x1Cord": "929", "y0Cord": "1031", "y1Cord": "1079", "img": "Screen6.png"}, "id": "6", "frame": "", "fatherIndex": "4", "fatherName": "If-Exist", "extra": "", "indention": 3}]}, "indention": 2}, {"name": "{", "img": "", "id": "5", "frame": "", "fatherIndex": "4", "fatherName": "If-Exist", "extra": "", "indention": 2}, {"name": "Left-Click", "img": {"x0Cord": "866", "x1Cord": "929", "y0Cord": "1031", "y1Cord": "1079", "img": "Screen6.png"}, "id": "6", "frame": "", "fatherIndex": "4", "fatherName": "If-Exist", "extra": "", "indention": 3}, {"name": "}", "img": "", "id": "7", "frame": "", "fatherIndex": "4", "fatherName": "If-Exist", "extra": "", "indention": 2}]}, "indention": 1}, {"name": "{", "img": "", "id": "3", "frame": "", "fatherIndex": "2", "fatherName": "If-Exist", "extra": "", "indention": 1}, {"name": "If-Exist", "img": {"x0Cord": "742", "x1Cord": "796", "y0Cord": "1032", "y1Cord": "1079", "img": "Screen4.png"}, "id": "4", "frame": "", "fatherIndex": "2", "fatherName": "If-Exist", "extra": {"image": "Screen4.png", "functions": [{"name": "Left-Click", "img": {"x0Cord": "866", "x1Cord": "929", "y0Cord": "1031", "y1Cord": "1079", "img": "Screen6.png"}, "id": "6", "frame": "", "fatherIndex": "4", "fatherName": "If-Exist", "extra": "", "indention": 3}]}, "indention": 2}, {"name": "{", "img": "", "id": "5", "frame": "", "fatherIndex": "4", "fatherName": "If-Exist", "extra": "", "indention": 2}, {"name": "Left-Click", "img": {"x0Cord": "866", "x1Cord": "929", "y0Cord": "1031", "y1Cord": "1079", "img": "Screen6.png"}, "id": "6", "frame": "", "fatherIndex": "4", "fatherName": "If-Exist", "extra": "", "indention": 3}, {"name": "}", "img": "", "id": "7", "frame": "", "fatherIndex": "4", "fatherName": "If-Exist", "extra": "", "indention": 2}, {"name": "}", "img": "", "id": "8", "frame": "", "fatherIndex": "2", "fatherName": "If-Exist", "extra": "", "indention": 1}]}, "indention": 0}, {"name": "{", "img": "", "id": "1", "frame": "", "fatherIndex": "0", "fatherName": "If-Exist", "extra": "", "indention": 0}, {"name": "If-Exist", "img": {"x0Cord": "804", "x1Cord": "861", "y0Cord": "1031", "y1Cord": "1079", "img": "Screen2.png"}, "id": "2", "frame": "", "fatherIndex": "0", "fatherName": "If-Exist", "extra": {"image": "Screen2.png", "functions": [{"name": "If-Exist", "img": {"x0Cord": "742", "x1Cord": "796", "y0Cord": "1032", "y1Cord": "1079", "img": "Screen4.png"}, "id": "4", "frame": "", "fatherIndex": "2", "fatherName": "If-Exist", "extra": {"image": "Screen4.png", "functions": [{"name": "Left-Click", "img": {"x0Cord": "866", "x1Cord": "929", "y0Cord": "1031", "y1Cord": "1079", "img": "Screen6.png"}, "id": "6", "frame": "", "fatherIndex": "4", "fatherName": "If-Exist", "extra": "", "indention": 3}]}, "indention": 2}, {"name": "{", "img": "", "id": "5", "frame": "", "fatherIndex": "4", "fatherName": "If-Exist", "extra": "", "indention": 2}, {"name": "Left-Click", "img": {"x0Cord": "866", "x1Cord": "929", "y0Cord": "1031", "y1Cord": "1079", "img": "Screen6.png"}, "id": "6", "frame": "", "fatherIndex": "4", "fatherName": "If-Exist", "extra": "", "indention": 3}, {"name": "}", "img": "", "id": "7", "frame": "", "fatherIndex": "4", "fatherName": "If-Exist", "extra": "", "indention": 2}]}, "indention": 1}, {"name": "{", "img": "", "id": "3", "frame": "", "fatherIndex": "2", "fatherName": "If-Exist", "extra": "", "indention": 1}, {"name": "If-Exist", "img": {"x0Cord": "742", "x1Cord": "796", "y0Cord": "1032", "y1Cord": "1079", "img": "Screen4.png"}, "id": "4", "frame": "", "fatherIndex": "2", "fatherName": "If-Exist", "extra": {"image": "Screen4.png", "functions": [{"name": "Left-Click", "img": {"x0Cord": "866", "x1Cord": "929", "y0Cord": "1031", "y1Cord": "1079", "img": "Screen6.png"}, "id": "6", "frame": "", "fatherIndex": "4", "fatherName": "If-Exist", "extra": "", "indention": 3}]}, "indention": 2}, {"name": "{", "img": "", "id": "5", "frame": "", "fatherIndex": "4", "fatherName": "If-Exist", "extra": "", "indention": 2}, {"name": "Left-Click", "img": {"x0Cord": "866", "x1Cord": "929", "y0Cord": "1031", "y1Cord": "1079", "img": "Screen6.png"}, "id": "6", "frame": "", "fatherIndex": "4", "fatherName": "If-Exist", "extra": "", "indention": 3}, {"name": "}", "img": "", "id": "7", "frame": "", "fatherIndex": "4", "fatherName": "If-Exist", "extra": "", "indention": 2}, {"name": "}", "img": "", "id": "8", "frame": "", "fatherIndex": "2", "fatherName": "If-Exist", "extra": "", "indention": 1}, {"name": "}", "img": "", "id": "9", "frame": "", "fatherIndex": "0", "fatherName": "If-Exist", "extra": "", "indention": 0}]
[{"fatherName": "If-Exist", "fromIndex": 0, "toIndex": 9}, {"fatherName": "If-Exist", "fromIndex": 0, "toIndex": 9}, {"fatherName": "If-Exist", "fromIndex": 2, "toIndex": 8}, {"fatherName": "If-Exist", "fromIndex": 2, "toIndex": 8}, {"fatherName": "If-Exist", "fromIndex": 4, "toIndex": 7}, {"fatherName": "If-Exist", "fromIndex": 4, "toIndex": 7}, {"fatherName": "If-Exist", "fromIndex": 4, "toIndex": 7}, {"fatherName": "If-Exist", "fromIndex": 4, "toIndex": 7}, {"fatherName": "If-Exist", "fromIndex": 2, "toIndex": 8}, {"fatherName": "If-Exist", "fromIndex": 0, "toIndex": 9}]